setup.py
heraspy/__init__.py
heraspy/callback.py
heraspy/model.py
heraspy.egg-info/PKG-INFO
heraspy.egg-info/SOURCES.txt
heraspy.egg-info/dependency_links.txt
heraspy.egg-info/requires.txt
heraspy.egg-info/top_level.txt