Metadata-Version: 1.0
Name: heraspy
Version: 0.2
Summary: Keras data extraction callbacks
Home-page: UNKNOWN
Author: Jake Bian
Author-email: jake@getalkanet.com
License: wtfpl
Platform: any
